lzy_stock_env/__init__.py
lzy_stock_env/envs/__init__.py
lzy_stock_env/envs/stock_env.py
lzy_stock_env-1.6.8.dist-info/METADATA
lzy_stock_env-1.6.8.dist-info/WHEEL
lzy_stock_env-1.6.8.dist-info/top_level.txt
lzy_stock_env-1.6.8.dist-info/RECORD
